UniProtMapper/__init__.py
UniProtMapper/_version.py
UniProtMapper/api.py
UniProtMapper/cli.py
UniProtMapper/interface.py
UniProtMapper/utils.py
UniProtMapper/version_helper.py
UniProtMapper/resources/cli_return_fields.txt
UniProtMapper/resources/uniprot_crossref_details.json
UniProtMapper/resources/uniprot_mapping_dbs.json
UniProtMapper/resources/uniprot_return_fields.csv
uniprot_id_mapper-1.1.2.dist-info/LICENSE
uniprot_id_mapper-1.1.2.dist-info/METADATA
uniprot_id_mapper-1.1.2.dist-info/WHEEL
uniprot_id_mapper-1.1.2.dist-info/entry_points.txt
uniprot_id_mapper-1.1.2.dist-info/top_level.txt
uniprot_id_mapper-1.1.2.dist-info/RECORD
