Metadata-Version: 2.1
Name: uniprot-id-mapper
Version: 1.1.2
Summary: A Python wrapper for the UniProt Mapping RESTful API.
Author-email: David Araripe <david.araripe17@gmail.com>
Maintainer-email: David Araripe <david.araripe17@gmail.com>
License: MIT License
Project-URL: homepage, https://github.com/David-Araripe/UniProtMapper
Project-URL: repository, https://github.com/David-Araripe/UniProtMapper
Keywords: uniprot,database,protein ID,gene ID,parser
Classifier: Development Status :: 5 - Production/Stable
Classifier: License :: OSI Approved :: MIT License
Classifier: Operating System :: OS Independent
Classifier: Programming Language :: Python :: 3.12
Classifier: Programming Language :: Python :: 3.11
Classifier: Programming Language :: Python :: 3.10
Classifier: Programming Language :: Python :: 3.9
Classifier: Programming Language :: Python :: 3.8
Classifier: Programming Language :: Python :: 3.7
Requires-Python: >=3.7
License-File: LICENSE
Requires-Dist: requests
Requires-Dist: pandas
Requires-Dist: numpy
Provides-Extra: dev
Requires-Dist: ruff ; extra == 'dev'
Requires-Dist: isort ; extra == 'dev'
Requires-Dist: black ; extra == 'dev'
